{"id":17393,"unique_id":"17393-3914","author":{"id":321968,"username":"Javipepe","avatar":"https://www.gravatar.com/avatar/f4650cbe1fb771bf10f79da4aa2d56f7?s=$SIZE$\u0026default=mm","color":"none","staff":false},"body":"Hello.\u003cbr\u003e\u003cbr\u003eWe are recently being targeted by a numerous group of alts of a banned player which is sending keyloggers where from they can get everything you are typing plus get your\u0026nbsp;IP, and probably get DDoS'd by someone.\u003cbr\u003e\u003cbr\u003eIf you don't want your ip exposed or people to get your passwords. Please don't click any links in chat unless you\u0026nbsp;\u003cb\u003ereally really really\u0026nbsp;\u003c/b\u003etrust their origin, like imgur.com, avicus.net. But never things like adf.ly or goo.gl.\u003cbr\u003e\u003cbr\u003eYou are responsible for your actions, thus that implies that is not our responsibility, and that we will be permanently banning people doing this, but meanwhile\u003cb\u003e\u003ci\u003e take care, please.\u003c/i\u003e\u003c/b\u003e","body_tagged":"Hello.\u003cbr\u003e\u003cbr\u003eWe are recently being targeted by a numerous group of alts of a banned player which is sending keyloggers where from they can get everything you are typing plus get your\u0026nbsp;IP, and probably get DDoS'd by someone.\u003cbr\u003e\u003cbr\u003eIf you don't want your ip exposed or people to get your passwords. Please don't click any links in chat unless you\u0026nbsp;\u003cb\u003ereally really really\u0026nbsp;\u003c/b\u003etrust their origin, like imgur.com, avicus.net. But never things like adf.ly or goo.gl.\u003cbr\u003e\u003cbr\u003eYou are responsible for your actions, thus that implies that is not our responsibility, and that we will be permanently banning people doing this, but meanwhile\u003cb\u003e\u003ci\u003e take care, please.\u003c/i\u003e\u003c/b\u003e","created_at":"2015/10/16 17:15:56 +0000","created_at_human":"October 16, 2015 at  5:10 PM UTC","title":"[IMPORTANT] Alert for keyloggers.","replies":[]}