{"id":4596,"unique_id":"4596-256","author":{"id":128245,"username":"OmniDom","avatar":"https://crafatar.com/avatars/c387bef1e48642248be9bc8aadd1890d?helm\u0026size=$SIZE$","color":"none","staff":false},"body":"So many rumors have been going around about a change in the donor perks, or user benefits changing.\u003cbr\u003eI'm sure many others are wondering what is really happening, I have no clue, but if someone with authority, or insight could tell us whats happening on the first of august (tomorrow)that would be greatly appreciated.\u003cbr\u003ethanks,\u003cbr\u003eDom","body_tagged":"So many rumors have been going around about a change in the donor perks, or user benefits changing.\u003cbr\u003eI'm sure many others are wondering what is really happening, I have no clue, but if someone with authority, or insight could tell us whats happening on the first of august (tomorrow)that would be greatly appreciated.\u003cbr\u003ethanks,\u003cbr\u003eDom","created_at":"2014/08/01 01:35:21 +0000","created_at_human":"August  1, 2014 at  1:08 AM UTC","title":"EULA Server Change","replies":[{"id":54029,"unique_id":"54029-4199","author":{"id":163667,"username":"goldenwalrus909","avatar":"https://www.gravatar.com/avatar/d27d79b3a7444e15bc68cf75e9ebcb97?s=$SIZE$\u0026default=mm","color":"none","staff":false},"body":"Yeah, I'm pretty curious, too..\u003cbr\u003eI guess we'll just have to wait and see :3","body_tagged":"Yeah, I'm pretty curious, too..\u003cbr\u003eI guess we'll just have to wait and see :3","created_at":"2014/08/01 02:00:10 +0000","created_at_human":"August  1, 2014 at  2:08 AM UTC"},{"id":54030,"unique_id":"54030-4028","author":{"id":103,"username":"Shoto_","avatar":"https://crafatar.com/avatars/c959860f3ff34258b68d2a9e4541572f?helm\u0026size=$SIZE$","color":"none","staff":false},"body":"There's going to be a change in donator perks, not sure what else though. We'll have to wait and see.","body_tagged":"There's going to be a change in donator perks, not sure what else though. We'll have to wait and see.","created_at":"2014/08/01 02:00:43 +0000","created_at_human":"August  1, 2014 at  2:08 AM UTC"},{"id":54032,"unique_id":"54032-1814","author":{"id":13076,"username":"Precise_","avatar":"https://crafatar.com/avatars/bacada7ea6e84e969b831ce159030e11?helm\u0026size=$SIZE$","color":"#5D5D5D","staff":false},"body":"August 1st :o","body_tagged":"August 1st :o","created_at":"2014/08/01 02:02:16 +0000","created_at_human":"August  1, 2014 at  2:08 AM UTC"},{"id":54084,"unique_id":"54084-704","author":{"id":18306,"username":"Gforce40","avatar":"https://crafatar.com/avatars/c827c1f4482e4f889f689791f6422a45?helm\u0026size=$SIZE$","color":"none","staff":false},"body":"No exp boost and no donor kits. For this server,\u0026nbsp;\u003ci\u003ethat's pretty much it.\u0026nbsp;\u003c/i\u003eAlso I think you can't join full games. Not sure about that one.","body_tagged":"No exp boost and no donor kits. For this server,\u0026nbsp;\u003ci\u003ethat's pretty much it.\u0026nbsp;\u003c/i\u003eAlso I think you can't join full games. Not sure about that one.","created_at":"2014/08/01 03:47:18 +0000","created_at_human":"August  1, 2014 at  3:08 AM UTC"},{"id":54088,"unique_id":"54088-2310","author":{"id":128245,"username":"OmniDom","avatar":"https://crafatar.com/avatars/c387bef1e48642248be9bc8aadd1890d?helm\u0026size=$SIZE$","color":"none","staff":false},"body":"the suspense builds....","body_tagged":"the suspense builds....","created_at":"2014/08/01 04:01:54 +0000","created_at_human":"August  1, 2014 at  4:08 AM UTC"},{"id":54090,"unique_id":"54090-2192","author":{"id":5921,"username":"cinammoncroc000","avatar":"https://www.gravatar.com/avatar/e78fa6765bb5a469eb39882239347fd3?s=$SIZE$\u0026default=mm","color":"Gray","staff":true},"body":"The only way that would affect gameplay is team-stacking. But then again, I could be wrong :P","body_tagged":"The only way that would affect gameplay is team-stacking. But then again, I could be wrong :P","created_at":"2014/08/01 04:05:07 +0000","created_at_human":"August  1, 2014 at  4:08 AM UTC","reply_to":{"id":54084,"unique_id":"54084-4669","author":{"id":18306,"username":"Gforce40","avatar":"https://crafatar.com/avatars/c827c1f4482e4f889f689791f6422a45?helm\u0026size=$SIZE$","color":"none","staff":false},"body":"No exp boost and no donor kits. For this server,\u0026nbsp;\u003ci\u003ethat's pretty much it.\u0026nbsp;\u003c/i\u003eAlso I think you can't join full games. Not sure about that one.","body_tagged":"No exp boost and no donor kits. For this server,\u0026nbsp;\u003ci\u003ethat's pretty much it.\u0026nbsp;\u003c/i\u003eAlso I think you can't join full games. Not sure about that one.","created_at":"2014/08/01 03:47:18 +0000","created_at_human":"August  1, 2014 at  3:08 AM UTC"}},{"id":54091,"unique_id":"54091-2211","author":{"id":6361,"username":"Emmaye","avatar":"https://www.gravatar.com/avatar/abed267c620d5e6347952892f3431f7b?s=$SIZE$\u0026default=mm","color":"Gray","staff":true},"body":"its august 1st where I am :o","body_tagged":"its august 1st where I am :o","created_at":"2014/08/01 04:08:25 +0000","created_at_human":"August  1, 2014 at  4:08 AM UTC"},{"id":54095,"unique_id":"54095-3733","author":{"id":244350,"username":"Phobiaxx","avatar":"https://www.gravatar.com/avatar/312a0024b8d891a0b8b86e30c296b28d?s=$SIZE$\u0026default=mm","color":"none","staff":false},"body":"I hope our player count doesn't decrease :c","body_tagged":"I hope our player count doesn't decrease :c","created_at":"2014/08/01 04:15:13 +0000","created_at_human":"August  1, 2014 at  4:08 AM UTC"},{"id":54142,"unique_id":"54142-957","author":{"id":3845,"username":"Sphrynax","avatar":"https://crafatar.com/avatars/97eb98011f844c6e87bc85e3afe32adc?helm\u0026size=$SIZE$","color":"#5D5D5D","staff":false},"body":"So what would donors get back?\u003cbr\u003eLet's say it was august 1st, would I get $100 back? Or what?","body_tagged":"So what would donors get back?\u003cbr\u003eLet's say it was august 1st, would I get $100 back? Or what?","created_at":"2014/08/01 05:45:50 +0000","created_at_human":"August  1, 2014 at  5:08 AM UTC"},{"id":54145,"unique_id":"54145-3431","author":{"id":112,"username":"Awarrior","avatar":"https://crafatar.com/avatars/6ceda19d312c4b42aee3acbdf9c9fc13?helm\u0026size=$SIZE$","color":"#5D5D5D","staff":false},"body":"I doubt,\u003cbr\u003e\u003cbr\u003edont get too heated however, the replacement will be sweet. \u0026nbsp;\u003cbr\u003e\u003cbr\u003eIf replacement there is!","body_tagged":"I doubt,\u003cbr\u003e\u003cbr\u003edont get too heated however, the replacement will be sweet. \u0026nbsp;\u003cbr\u003e\u003cbr\u003eIf replacement there is!","created_at":"2014/08/01 05:48:03 +0000","created_at_human":"August  1, 2014 at  5:08 AM UTC","reply_to":{"id":54142,"unique_id":"54142-3457","author":{"id":3845,"username":"Sphrynax","avatar":"https://crafatar.com/avatars/97eb98011f844c6e87bc85e3afe32adc?helm\u0026size=$SIZE$","color":"#5D5D5D","staff":false},"body":"So what would donors get back?\u003cbr\u003eLet's say it was august 1st, would I get $100 back? Or what?","body_tagged":"So what would donors get back?\u003cbr\u003eLet's say it was august 1st, would I get $100 back? Or what?","created_at":"2014/08/01 05:45:50 +0000","created_at_human":"August  1, 2014 at  5:08 AM UTC"}},{"id":54148,"unique_id":"54148-4274","author":{"id":103,"username":"Shoto_","avatar":"https://crafatar.com/avatars/c959860f3ff34258b68d2a9e4541572f?helm\u0026size=$SIZE$","color":"none","staff":false},"body":"There is a replacement, just not sure what it'll be. Right now, it's August 1st in Sweden.","body_tagged":"There is a replacement, just not sure what it'll be. Right now, it's August 1st in Sweden.","created_at":"2014/08/01 06:01:04 +0000","created_at_human":"August  1, 2014 at  6:08 AM UTC"},{"id":54149,"unique_id":"54149-952","author":{"id":112,"username":"Awarrior","avatar":"https://crafatar.com/avatars/6ceda19d312c4b42aee3acbdf9c9fc13?helm\u0026size=$SIZE$","color":"#5D5D5D","staff":false},"body":"August 1st in Canada!","body_tagged":"August 1st in Canada!","created_at":"2014/08/01 06:01:54 +0000","created_at_human":"August  1, 2014 at  6:08 AM UTC","reply_to":{"id":54148,"unique_id":"54148-1211","author":{"id":103,"username":"Shoto_","avatar":"https://crafatar.com/avatars/c959860f3ff34258b68d2a9e4541572f?helm\u0026size=$SIZE$","color":"none","staff":false},"body":"There is a replacement, just not sure what it'll be. Right now, it's August 1st in Sweden.","body_tagged":"There is a replacement, just not sure what it'll be. Right now, it's August 1st in Sweden.","created_at":"2014/08/01 06:01:04 +0000","created_at_human":"August  1, 2014 at  6:08 AM UTC"}},{"id":54150,"unique_id":"54150-1830","author":{"id":103,"username":"Shoto_","avatar":"https://crafatar.com/avatars/c959860f3ff34258b68d2a9e4541572f?helm\u0026size=$SIZE$","color":"none","staff":false},"body":"Yep, 2 hours in August 1st here, too.","body_tagged":"Yep, 2 hours in August 1st here, too.","created_at":"2014/08/01 06:13:01 +0000","created_at_human":"August  1, 2014 at  6:08 AM UTC","reply_to":{"id":54149,"unique_id":"54149-3448","author":{"id":112,"username":"Awarrior","avatar":"https://crafatar.com/avatars/6ceda19d312c4b42aee3acbdf9c9fc13?helm\u0026size=$SIZE$","color":"#5D5D5D","staff":false},"body":"August 1st in Canada!","body_tagged":"August 1st in Canada!","created_at":"2014/08/01 06:01:54 +0000","created_at_human":"August  1, 2014 at  6:08 AM UTC"}},{"id":54152,"unique_id":"54152-1623","author":{"id":250394,"username":"StaticFaultz","avatar":"https://crafatar.com/avatars/5f8aeb60e33742ca90a94104cccb4d2a?helm\u0026size=$SIZE$","color":"none","staff":false},"body":"Only thing that may change is the kits as they are not cosmetic changes.","body_tagged":"Only thing that may change is the kits as they are not cosmetic changes.","created_at":"2014/08/01 06:29:42 +0000","created_at_human":"August  1, 2014 at  6:08 AM UTC"},{"id":54189,"unique_id":"54189-525","author":{"id":317175,"username":"Arachadonic","avatar":"https://crafatar.com/avatars/9e449b182d894146ad543fb89c7c647d?helm\u0026size=$SIZE$","color":"none","staff":false},"body":"I would like to know to be honest and I feel like we deserve to know since it was our money we spent. Don't get me wrong I don't want a refund but I would like to know what is being done about it.","body_tagged":"I would like to know to be honest and I feel like we deserve to know since it was our money we spent. Don't get me wrong I don't want a refund but I would like to know what is being done about it.","created_at":"2014/08/01 10:42:30 +0000","created_at_human":"August  1, 2014 at 10:08 AM UTC"},{"id":54192,"unique_id":"54192-4053","author":{"id":3453,"username":"build_high","avatar":"https://crafatar.com/avatars/6369af3c96324c1d81be990de7a017ac?helm\u0026size=$SIZE$","color":"none","staff":false},"body":"Your rank will be purely for aesthetics and fun, anything that gives a donator an advantage etc. premium kits or xp boosts in a kitted minigame (nebula may still have xp boost because it has no kits)\u003cbr\u003eso all the gameplay changing aspects will be removed, they may be replaced with trails, pets or hats in the lobby.","body_tagged":"Your rank will be purely for aesthetics and fun, anything that gives a donator an advantage etc. premium kits or xp boosts in a kitted minigame (nebula may still have xp boost because it has no kits)\u003cbr\u003eso all the gameplay changing aspects will be removed, they may be replaced with trails, pets or hats in the lobby.","created_at":"2014/08/01 10:49:40 +0000","created_at_human":"August  1, 2014 at 10:08 AM UTC","reply_to":{"id":54189,"unique_id":"54189-621","author":{"id":317175,"username":"Arachadonic","avatar":"https://crafatar.com/avatars/9e449b182d894146ad543fb89c7c647d?helm\u0026size=$SIZE$","color":"none","staff":false},"body":"I would like to know to be honest and I feel like we deserve to know since it was our money we spent. Don't get me wrong I don't want a refund but I would like to know what is being done about it.","body_tagged":"I would like to know to be honest and I feel like we deserve to know since it was our money we spent. Don't get me wrong I don't want a refund but I would like to know what is being done about it.","created_at":"2014/08/01 10:42:30 +0000","created_at_human":"August  1, 2014 at 10:08 AM UTC"}},{"id":54196,"unique_id":"54196-1161","author":{"id":317175,"username":"Arachadonic","avatar":"https://crafatar.com/avatars/9e449b182d894146ad543fb89c7c647d?helm\u0026size=$SIZE$","color":"none","staff":false},"body":"Not necessarily.. If they let non-donors get the kits/exp boost but make it really hard then we can keep what we paid for.\u003cbr\u003e\u003cbr\u003eAlso no offense but I was really hoping for an official response from one of the Directors/Managers.","body_tagged":"Not necessarily.. If they let non-donors get the kits/exp boost but make it really hard then we can keep what we paid for.\u003cbr\u003e\u003cbr\u003eAlso no offense but I was really hoping for an official response from one of the Directors/Managers.","created_at":"2014/08/01 11:08:19 +0000","created_at_human":"August  1, 2014 at 11:08 AM UTC","reply_to":{"id":54192,"unique_id":"54192-3292","author":{"id":3453,"username":"build_high","avatar":"https://crafatar.com/avatars/6369af3c96324c1d81be990de7a017ac?helm\u0026size=$SIZE$","color":"none","staff":false},"body":"Your rank will be purely for aesthetics and fun, anything that gives a donator an advantage etc. premium kits or xp boosts in a kitted minigame (nebula may still have xp boost because it has no kits)\u003cbr\u003eso all the gameplay changing aspects will be removed, they may be replaced with trails, pets or hats in the lobby.","body_tagged":"Your rank will be purely for aesthetics and fun, anything that gives a donator an advantage etc. premium kits or xp boosts in a kitted minigame (nebula may still have xp boost because it has no kits)\u003cbr\u003eso all the gameplay changing aspects will be removed, they may be replaced with trails, pets or hats in the lobby.","created_at":"2014/08/01 10:49:40 +0000","created_at_human":"August  1, 2014 at 10:08 AM UTC"}},{"id":54199,"unique_id":"54199-3001","author":{"id":3453,"username":"build_high","avatar":"https://crafatar.com/avatars/6369af3c96324c1d81be990de7a017ac?helm\u0026size=$SIZE$","color":"none","staff":false},"body":"That's fine,\u003cbr\u003eand they won't give non donors the xp boosts (possibly access to the kits though) but If they make it really hard for non donors it would count as a gameplay altering advantage so.. :/","body_tagged":"That's fine,\u003cbr\u003eand they won't give non donors the xp boosts (possibly access to the kits though) but If they make it really hard for non donors it would count as a gameplay altering advantage so.. :/","created_at":"2014/08/01 11:29:14 +0000","created_at_human":"August  1, 2014 at 11:08 AM UTC","reply_to":{"id":54196,"unique_id":"54196-1375","author":{"id":317175,"username":"Arachadonic","avatar":"https://crafatar.com/avatars/9e449b182d894146ad543fb89c7c647d?helm\u0026size=$SIZE$","color":"none","staff":false},"body":"Not necessarily.. If they let non-donors get the kits/exp boost but make it really hard then we can keep what we paid for.\u003cbr\u003e\u003cbr\u003eAlso no offense but I was really hoping for an official response from one of the Directors/Managers.","body_tagged":"Not necessarily.. If they let non-donors get the kits/exp boost but make it really hard then we can keep what we paid for.\u003cbr\u003e\u003cbr\u003eAlso no offense but I was really hoping for an official response from one of the Directors/Managers.","created_at":"2014/08/01 11:08:19 +0000","created_at_human":"August  1, 2014 at 11:08 AM UTC"}},{"id":54200,"unique_id":"54200-2387","author":{"id":317175,"username":"Arachadonic","avatar":"https://crafatar.com/avatars/9e449b182d894146ad543fb89c7c647d?helm\u0026size=$SIZE$","color":"none","staff":false},"body":"Hypixel did it with their coin boosts that donors get and Mojang said it was okay.","body_tagged":"Hypixel did it with their coin boosts that donors get and Mojang said it was okay.","created_at":"2014/08/01 11:32:51 +0000","created_at_human":"August  1, 2014 at 11:08 AM UTC","reply_to":{"id":54199,"unique_id":"54199-1334","author":{"id":3453,"username":"build_high","avatar":"https://crafatar.com/avatars/6369af3c96324c1d81be990de7a017ac?helm\u0026size=$SIZE$","color":"none","staff":false},"body":"That's fine,\u003cbr\u003eand they won't give non donors the xp boosts (possibly access to the kits though) but If they make it really hard for non donors it would count as a gameplay altering advantage so.. :/","body_tagged":"That's fine,\u003cbr\u003eand they won't give non donors the xp boosts (possibly access to the kits though) but If they make it really hard for non donors it would count as a gameplay altering advantage so.. :/","created_at":"2014/08/01 11:29:14 +0000","created_at_human":"August  1, 2014 at 11:08 AM UTC"}},{"id":54224,"unique_id":"54224-168","author":{"id":128245,"username":"OmniDom","avatar":"https://crafatar.com/avatars/c387bef1e48642248be9bc8aadd1890d?helm\u0026size=$SIZE$","color":"none","staff":false},"body":"Exactly, you would think they know a little more than us and would want to share their knowledge..........","body_tagged":"Exactly, you would think they know a little more than us and would want to share their knowledge..........","created_at":"2014/08/01 12:46:06 +0000","created_at_human":"August  1, 2014 at 12:08 PM UTC","reply_to":{"id":54196,"unique_id":"54196-4921","author":{"id":317175,"username":"Arachadonic","avatar":"https://crafatar.com/avatars/9e449b182d894146ad543fb89c7c647d?helm\u0026size=$SIZE$","color":"none","staff":false},"body":"Not necessarily.. If they let non-donors get the kits/exp boost but make it really hard then we can keep what we paid for.\u003cbr\u003e\u003cbr\u003eAlso no offense but I was really hoping for an official response from one of the Directors/Managers.","body_tagged":"Not necessarily.. If they let non-donors get the kits/exp boost but make it really hard then we can keep what we paid for.\u003cbr\u003e\u003cbr\u003eAlso no offense but I was really hoping for an official response from one of the Directors/Managers.","created_at":"2014/08/01 11:08:19 +0000","created_at_human":"August  1, 2014 at 11:08 AM UTC"}},{"id":54282,"unique_id":"54282-3017","author":{"id":6564,"username":"kycrafft","avatar":"https://www.gravatar.com/avatar/b3bcefeeb60e1af497aa9a36dacbc965?s=$SIZE$\u0026default=mm","color":"none","staff":false},"body":"The xp boost must go as it directly affects gameplay (pretty sure Mojang mentioned donator multipliers in one of their statements). It allows donators to unlock kits faster. The donator kits obviously will have to be dropped. I think Avicus will be relatively untouched, so yay. Just worried about other servers.","body_tagged":"The xp boost must go as it directly affects gameplay (pretty sure Mojang mentioned donator multipliers in one of their statements). It allows donators to unlock kits faster. The donator kits obviously will have to be dropped. I think Avicus will be relatively untouched, so yay. Just worried about other servers.","created_at":"2014/08/01 15:40:01 +0000","created_at_human":"August  1, 2014 at  3:08 PM UTC"},{"id":54330,"unique_id":"54330-4873","author":{"id":80,"username":"keller183","avatar":"https://crafatar.com/avatars/bb15cd6a948f4896a12715174743f4de?helm\u0026size=$SIZE$","color":"none","staff":false},"body":"\u0026nbsp;I hope they just make it so all the kits are free, but make pyro, assassin and freezer at higher \u0026nbsp;lvls and maybe douse pyro a bit (pun intended)","body_tagged":"\u0026nbsp;I hope they just make it so all the kits are free, but make pyro, assassin and freezer at higher \u0026nbsp;lvls and maybe douse pyro a bit (pun intended)","created_at":"2014/08/01 17:16:06 +0000","created_at_human":"August  1, 2014 at  5:08 PM UTC","reply_to":{"id":54282,"unique_id":"54282-4838","author":{"id":6564,"username":"kycrafft","avatar":"https://www.gravatar.com/avatar/b3bcefeeb60e1af497aa9a36dacbc965?s=$SIZE$\u0026default=mm","color":"none","staff":false},"body":"The xp boost must go as it directly affects gameplay (pretty sure Mojang mentioned donator multipliers in one of their statements). It allows donators to unlock kits faster. The donator kits obviously will have to be dropped. I think Avicus will be relatively untouched, so yay. Just worried about other servers.","body_tagged":"The xp boost must go as it directly affects gameplay (pretty sure Mojang mentioned donator multipliers in one of their statements). It allows donators to unlock kits faster. The donator kits obviously will have to be dropped. I think Avicus will be relatively untouched, so yay. Just worried about other servers.","created_at":"2014/08/01 15:40:01 +0000","created_at_human":"August  1, 2014 at  3:08 PM UTC"}},{"id":54332,"unique_id":"54332-4597","author":{"id":79,"username":"hpux","avatar":"https://crafatar.com/avatars/bef7da1eda9a4092ac5a2ee30d12a65c?helm\u0026size=$SIZE$","color":"none","staff":false},"body":"Compared to a lot of other servers, we are barely affected by this. Don't worry.","body_tagged":"Compared to a lot of other servers, we are barely affected by this. Don't worry.","created_at":"2014/08/01 17:18:09 +0000","created_at_human":"August  1, 2014 at  5:08 PM UTC"},{"id":54344,"unique_id":"54344-4215","author":{"id":317175,"username":"Arachadonic","avatar":"https://crafatar.com/avatars/9e449b182d894146ad543fb89c7c647d?helm\u0026size=$SIZE$","color":"none","staff":false},"body":"I suppose you are right.\u003cbr\u003e\u003cbr\u003eSidenote: When did you resign Peachy?","body_tagged":"I suppose you are right.\u003cbr\u003e\u003cbr\u003eSidenote: When did you resign Peachy?","created_at":"2014/08/01 17:48:42 +0000","created_at_human":"August  1, 2014 at  5:08 PM UTC","reply_to":{"id":54332,"unique_id":"54332-592","author":{"id":79,"username":"hpux","avatar":"https://crafatar.com/avatars/bef7da1eda9a4092ac5a2ee30d12a65c?helm\u0026size=$SIZE$","color":"none","staff":false},"body":"Compared to a lot of other servers, we are barely affected by this. Don't worry.","body_tagged":"Compared to a lot of other servers, we are barely affected by this. Don't worry.","created_at":"2014/08/01 17:18:09 +0000","created_at_human":"August  1, 2014 at  5:08 PM UTC"}},{"id":54379,"unique_id":"54379-1533","author":{"id":329244,"username":"keenanjt","avatar":"https://crafatar.com/avatars/8242e55ecc6a458ab272a2b34918045f?helm\u0026size=$SIZE$","color":"#E77400","staff":true},"body":"We'll be making changes as stated before. It's not known when or what will be changing but we must be in accordance with the rules Mojang sets in place. We'll do whatever we can to keep everyone happy. A more official announcement will come soon and changes will come later this month or early next month.","body_tagged":"We'll be making changes as stated before. It's not known when or what will be changing but we must be in accordance with the rules Mojang sets in place. We'll do whatever we can to keep everyone happy. A more official announcement will come soon and changes will come later this month or early next month.","created_at":"2014/08/01 18:58:02 +0000","created_at_human":"August  1, 2014 at  6:08 PM UTC"},{"id":54381,"unique_id":"54381-3432","author":{"id":244350,"username":"Phobiaxx","avatar":"https://www.gravatar.com/avatar/312a0024b8d891a0b8b86e30c296b28d?s=$SIZE$\u0026default=mm","color":"none","staff":false},"body":"@ivy :o i thought the deadline was aug 1st","body_tagged":"@ivy :o i thought the deadline was aug 1st","created_at":"2014/08/01 18:59:56 +0000","created_at_human":"August  1, 2014 at  6:08 PM UTC"},{"id":54382,"unique_id":"54382-1835","author":{"id":110770,"username":"Kels","avatar":"https://crafatar.com/avatars/3068b01d45fc4e8f9340ab3b77c85546?helm\u0026size=$SIZE$","color":"none","staff":false},"body":"Joining full games is allowed according to EULA","body_tagged":"Joining full games is allowed according to EULA","created_at":"2014/08/01 19:03:08 +0000","created_at_human":"August  1, 2014 at  7:08 PM UTC","reply_to":{"id":54084,"unique_id":"54084-555","author":{"id":18306,"username":"Gforce40","avatar":"https://crafatar.com/avatars/c827c1f4482e4f889f689791f6422a45?helm\u0026size=$SIZE$","color":"none","staff":false},"body":"No exp boost and no donor kits. For this server,\u0026nbsp;\u003ci\u003ethat's pretty much it.\u0026nbsp;\u003c/i\u003eAlso I think you can't join full games. Not sure about that one.","body_tagged":"No exp boost and no donor kits. For this server,\u0026nbsp;\u003ci\u003ethat's pretty much it.\u0026nbsp;\u003c/i\u003eAlso I think you can't join full games. Not sure about that one.","created_at":"2014/08/01 03:47:18 +0000","created_at_human":"August  1, 2014 at  3:08 AM UTC"}},{"id":54383,"unique_id":"54383-1113","author":{"id":79,"username":"hpux","avatar":"https://crafatar.com/avatars/bef7da1eda9a4092ac5a2ee30d12a65c?helm\u0026size=$SIZE$","color":"none","staff":false},"body":"A few hours ago.","body_tagged":"A few hours ago.","created_at":"2014/08/01 19:03:11 +0000","created_at_human":"August  1, 2014 at  7:08 PM UTC","reply_to":{"id":54344,"unique_id":"54344-4207","author":{"id":317175,"username":"Arachadonic","avatar":"https://crafatar.com/avatars/9e449b182d894146ad543fb89c7c647d?helm\u0026size=$SIZE$","color":"none","staff":false},"body":"I suppose you are right.\u003cbr\u003e\u003cbr\u003eSidenote: When did you resign Peachy?","body_tagged":"I suppose you are right.\u003cbr\u003e\u003cbr\u003eSidenote: When did you resign Peachy?","created_at":"2014/08/01 17:48:42 +0000","created_at_human":"August  1, 2014 at  5:08 PM UTC"}},{"id":54387,"unique_id":"54387-14","author":{"id":317175,"username":"Arachadonic","avatar":"https://crafatar.com/avatars/9e449b182d894146ad543fb89c7c647d?helm\u0026size=$SIZE$","color":"none","staff":false},"body":"How come?\u003cbr\u003eSorry to go off-topic just seems random and is very surprising!","body_tagged":"How come?\u003cbr\u003eSorry to go off-topic just seems random and is very surprising!","created_at":"2014/08/01 19:12:04 +0000","created_at_human":"August  1, 2014 at  7:08 PM UTC","reply_to":{"id":54383,"unique_id":"54383-2394","author":{"id":79,"username":"hpux","avatar":"https://crafatar.com/avatars/bef7da1eda9a4092ac5a2ee30d12a65c?helm\u0026size=$SIZE$","color":"none","staff":false},"body":"A few hours ago.","body_tagged":"A few hours ago.","created_at":"2014/08/01 19:03:11 +0000","created_at_human":"August  1, 2014 at  7:08 PM UTC"}},{"id":54438,"unique_id":"54438-2434","author":{"id":150549,"username":"AtditC","avatar":"https://crafatar.com/avatars/fb57ed989f4140c78e61dee46d34d427?helm\u0026size=$SIZE$","color":"none","staff":false},"body":"No xp boost?\u003cbr\u003ei gunna leave","body_tagged":"No xp boost?\u003cbr\u003ei gunna leave","created_at":"2014/08/01 21:04:25 +0000","created_at_human":"August  1, 2014 at  9:08 PM UTC"}]}